<?xml version="1.0" encoding="ISO-8859-1"  standalone="yes" ?>
<suivicomp>
  <sauvegarde ref="56d033cd4f7ba">
    <ref>56d033cd4f7ba</ref>
    <datesv>2016-02-26</datesv>
  </sauvegarde>
  <etudiant numero="110">
    <nom>GUYAMIER</nom>
    <prenom>Thomas</prenom>
    <mel>thomas.guyamier@icof.fr</mel>
    <situation ref="646">
      <ref>646</ref>
      <codeType>1</codeType>
      <codeLocalisation>1</codeLocalisation>
      <codeSource>1</codeSource>
      <codeCadre>2</codeCadre>
      <libcourt>Stage 1 SOMECI </libcourt>
      <descriptif>Refonte d'un site intranet</descriptif>
      <contexte>Stage de 1er années</contexte>
      <datedebut>2015-05-18</datedebut>
      <datefin>2015-06-26</datefin>
      <environnement>IDE : &quot;WebDev&quot; - Gestion des donnée : Web service - Navigateur : Mozilla Firefox</environnement>
      <moyen></moyen>
      <avisperso></avisperso>
      <activitecitee numero="1">
        <idActivite>1</idActivite>
        <commentaireactivite>Analyse des fonctionnalité existente de l'ancien intranet, qui peuvent être incorporer dans le nouveau site</commentaireactivite>
      </activitecitee>
      <activitecitee numero="5">
        <idActivite>5</idActivite>
        <commentaireactivite></commentaireactivite>
      </activitecitee>
      <activitecitee numero="8">
        <idActivite>8</idActivite>
        <commentaireactivite>Architecture du site basé sur des étage de connexion et de droits</commentaireactivite>
      </activitecitee>
      <activitecitee numero="9">
        <idActivite>9</idActivite>
        <commentaireactivite>Réalisation des fonction premièrement sur la maquette puis importation des fonctionnalité tester et fonctionnel sur le projet final</commentaireactivite>
      </activitecitee>
      <activitecitee numero="12">
        <idActivite>12</idActivite>
        <commentaireactivite>Mise en place du déploiement et déploiment via la fonction &quot;Déploiement&quot; sur webdev</commentaireactivite>
      </activitecitee>
      <activitecitee numero="13">
        <idActivite>13</idActivite>
        <commentaireactivite>Ecrit sur les analyse des fonctionnalité et prise de décision sur les tâche garder avec mon maître de stage</commentaireactivite>
      </activitecitee>
      <activitecitee numero="34">
        <idActivite>34</idActivite>
        <commentaireactivite>Lecteur RSS</commentaireactivite>
      </activitecitee>
      <activitecitee numero="35">
        <idActivite>35</idActivite>
        <commentaireactivite>Choix du css et de arrangement des pages</commentaireactivite>
      </activitecitee>
      <activitecitee numero="36">
        <idActivite>36</idActivite>
        <commentaireactivite>Analyse des fonctionalité du SGBD de Webdev pour un prototype de blog d'entreprise</commentaireactivite>
      </activitecitee>
      <activitecitee numero="38">
        <idActivite>38</idActivite>
        <commentaireactivite>Prototypage des fonctionalité (ex : page contact) sur premierement la maquette puis intégration de celle-ci dans le site final</commentaireactivite>
      </activitecitee>
      <activitecitee numero="39">
        <idActivite>39</idActivite>
        <commentaireactivite>WEBDEV</commentaireactivite>
      </activitecitee>
      <activitecitee numero="40">
        <idActivite>40</idActivite>
        <commentaireactivite>Dévelopement du site</commentaireactivite>
      </activitecitee>
      <activitecitee numero="41">
        <idActivite>41</idActivite>
        <commentaireactivite>Test élaboré sur les pages.</commentaireactivite>
      </activitecitee>
      <activitecitee numero="46">
        <idActivite>46</idActivite>
        <commentaireactivite></commentaireactivite>
      </activitecitee>
      <activitecitee numero="55">
        <idActivite>55</idActivite>
        <commentaireactivite>Appygeek, information sur les derniere téchnologie</commentaireactivite>
      </activitecitee>
      <activitecitee numero="57">
        <idActivite>57</idActivite>
        <commentaireactivite>RSS et WebService</commentaireactivite>
      </activitecitee>
      <production numero="1337">
        <numero>1337</numero>
        <designation>Accueil</designation>
        <adresse></adresse>
      </production>
      <typologie>
        <codeTypologie>1</codeTypologie>
      </typologie>
    </situation>
    <situation ref="736">
      <ref>736</ref>
      <codeType>1</codeType>
      <codeLocalisation>1</codeLocalisation>
      <codeSource>2</codeSource>
      <codeCadre>1</codeCadre>
      <libcourt>Stage 2 Tripconnexion</libcourt>
      <descriptif>Création de la 2éme version du site www.tripconnexion.com</descriptif>
      <contexte>Stage de 2ème année</contexte>
      <datedebut>2016-01-11</datedebut>
      <datefin>2016-02-26</datefin>
      <environnement>CMS : WordPress - IDE : Sublime3 - Naviguateur : Chrome, Mozilla - Technologie : HTML5,CSS,Javascript,PHP - Plugin : Bootstrap, Jquery(and addons), </environnement>
      <moyen></moyen>
      <avisperso></avisperso>
      <activitecitee numero="3">
        <idActivite>3</idActivite>
        <commentaireactivite></commentaireactivite>
      </activitecitee>
      <activitecitee numero="4">
        <idActivite>4</idActivite>
        <commentaireactivite></commentaireactivite>
      </activitecitee>
      <activitecitee numero="5">
        <idActivite>5</idActivite>
        <commentaireactivite></commentaireactivite>
      </activitecitee>
      <activitecitee numero="18">
        <idActivite>18</idActivite>
        <commentaireactivite></commentaireactivite>
      </activitecitee>
      <activitecitee numero="20">
        <idActivite>20</idActivite>
        <commentaireactivite></commentaireactivite>
      </activitecitee>
      <activitecitee numero="21">
        <idActivite>21</idActivite>
        <commentaireactivite></commentaireactivite>
      </activitecitee>
      <activitecitee numero="22">
        <idActivite>22</idActivite>
        <commentaireactivite></commentaireactivite>
      </activitecitee>
      <activitecitee numero="34">
        <idActivite>34</idActivite>
        <commentaireactivite>Album photo, besoin niveau Jquery addons et technologie utiliser pour l'upload et le rechargement de l'album</commentaireactivite>
      </activitecitee>
      <activitecitee numero="35">
        <idActivite>35</idActivite>
        <commentaireactivite>Maquette photoshop</commentaireactivite>
      </activitecitee>
      <activitecitee numero="36">
        <idActivite>36</idActivite>
        <commentaireactivite>Modification bdd table de jointure wp_partenaire_photo  </commentaireactivite>
      </activitecitee>
      <activitecitee numero="37">
        <idActivite>37</idActivite>
        <commentaireactivite>fiche sur les technologies utiliser</commentaireactivite>
      </activitecitee>
      <activitecitee numero="38">
        <idActivite>38</idActivite>
        <commentaireactivite>utilisation de masonry a  la place de jmosaic</commentaireactivite>
      </activitecitee>
      <activitecitee numero="39">
        <idActivite>39</idActivite>
        <commentaireactivite>Sublimetext 3 avec installtion de plugin</commentaireactivite>
      </activitecitee>
      <activitecitee numero="40">
        <idActivite>40</idActivite>
        <commentaireactivite>Developpement de l'album photo, page de connexion et inscription, template article</commentaireactivite>
      </activitecitee>
      <activitecitee numero="42">
        <idActivite>42</idActivite>
        <commentaireactivite></commentaireactivite>
      </activitecitee>
      <activitecitee numero="43">
        <idActivite>43</idActivite>
        <commentaireactivite></commentaireactivite>
      </activitecitee>
      <activitecitee numero="44">
        <idActivite>44</idActivite>
        <commentaireactivite></commentaireactivite>
      </activitecitee>
      <activitecitee numero="53">
        <idActivite>53</idActivite>
        <commentaireactivite></commentaireactivite>
      </activitecitee>
      <activitecitee numero="55">
        <idActivite>55</idActivite>
        <commentaireactivite></commentaireactivite>
      </activitecitee>
      <activitecitee numero="57">
        <idActivite>57</idActivite>
        <commentaireactivite></commentaireactivite>
      </activitecitee>
      <typologie>
        <codeTypologie>1</codeTypologie>
      </typologie>
      <typologie>
        <codeTypologie>2</codeTypologie>
      </typologie>
      <typologie>
        <codeTypologie>3</codeTypologie>
      </typologie>
    </situation>
  </etudiant>
</suivicomp>
